tweener/__init__.py
tweener/ease.py
tweener/ease2.py
tweener/tween.py
tweener-1.0.4.dist-info/METADATA
tweener-1.0.4.dist-info/WHEEL
tweener-1.0.4.dist-info/top_level.txt
tweener-1.0.4.dist-info/RECORD
