Metadata-Version: 2.1
Name: tweener
Version: 1.0.4
Summary: Helper functions for easing and tweening
Home-page: UNKNOWN
Author: Gin Ryu Rabino
Author-email: ginryurabino@gmail.com
License: UNKNOWN
Keywords: python,animation,easing
Platform: UNKNOWN
